IBATS_BitMex_Feeder-0.4.1.dist-info/METADATA
IBATS_BitMex_Feeder-0.4.1.dist-info/RECORD
IBATS_BitMex_Feeder-0.4.1.dist-info/WHEEL
IBATS_BitMex_Feeder-0.4.1.dist-info/top_level.txt
ibats_bitmex_feeder/__init__.py
ibats_bitmex_feeder/config.py
ibats_bitmex_feeder/feeder.py
ibats_bitmex_feeder/backend/__init__.py
ibats_bitmex_feeder/backend/bitmex_ws.py
ibats_bitmex_feeder/backend/check.py
ibats_bitmex_feeder/backend/handler.py
ibats_bitmex_feeder/backend/orm.py
ibats_bitmex_feeder/backend/other_tables.py
ibats_bitmex_feeder/utils/__init__.py
ibats_bitmex_feeder/utils/mess.py
