Metadata-Version: 2.1
Name: IBATS-BitMex-Feeder
Version: 0.4.1
Summary: 连接BitMex交易所，获取实时行情、历史行情，保存到mysql数据库同时redis广播，供 ABAT 交易平台进行策略回测、分析，交易使用
Home-page: https://github.com/IBATS/IBATS_BitMexFeeder
Author: MG
Author-email: mmmaaaggg@163.com
License: UNKNOWN
Platform: UNKNOWN
Classifier: Programming Language :: Python :: 3 :: Only
Classifier: Programming Language :: Python :: 3.6
Classifier: Programming Language :: Python :: 3.7
Classifier: Operating System :: Microsoft :: Windows
Classifier: Operating System :: Unix
Classifier: Operating System :: POSIX
Classifier: License :: OSI Approved :: MIT License
Classifier: Development Status :: 5 - Production/Stable
Classifier: Environment :: No Input/Output (Daemon)
Classifier: Intended Audience :: Developers
Classifier: Natural Language :: Chinese (Simplified)
Classifier: Topic :: Software Development
Requires-Python: >=3.6
Requires-Dist: websocket
Requires-Dist: msgpack (>=0.5.6)
Requires-Dist: websocket-client (>=0.46.0)
Requires-Dist: bitmex
Requires-Dist: bitmex-ws
Requires-Dist: IBATS-Common
Requires-Dist: mysqlclient (>=1.3.8)
Requires-Dist: numpy (==1.14.4)
Requires-Dist: pandas (==0.23.0)
Requires-Dist: prodconpattern (==0.1.1)
Requires-Dist: redis (==2.10.6)
Requires-Dist: SQLAlchemy (==1.2.8)
Requires-Dist: xlrd (==1.1.0)
